pymys/__init__.py
pymys/utils.py
pymys/mysensors.py
pymys/mys_16.py
pymys/mys_15.py
pymys-0.2.dist-info/WHEEL
pymys-0.2.dist-info/metadata.json
pymys-0.2.dist-info/top_level.txt
pymys-0.2.dist-info/RECORD
pymys-0.2.dist-info/DESCRIPTION.rst
pymys-0.2.dist-info/METADATA
