Metadata-Version: 2.0
Name: pymys
Version: 0.2
Summary: It is a module to make easier communication with MySensor's network.
Home-page: https://github.com/alfredocdmiranda/pymys
Author: Alfredo Miranda
Author-email: alfredocdmiranda@gmail.com
License: MIT
Keywords: MYS MySensors
Platform: UNKNOWN
Classifier: Development Status :: 1 - Planning
Classifier: Intended Audience :: Developers
Classifier: License :: OSI Approved :: MIT License
Classifier: Operating System :: POSIX :: Linux
Classifier: Programming Language :: Python
Classifier: Programming Language :: Python :: 3
Classifier: Programming Language :: Python :: 3.4
Classifier: Topic :: Software Development :: Libraries :: Python Modules
